CHANGES.rst
MANIFEST.in
README.rst
bootstrap.py
buildout.cfg
setup.cfg
setup.py
versions.cfg
docs/CONTRIBUTORS.rst
docs/INSTALL.txt
docs/LICENSE.GPL
docs/LICENSE.txt
unweb/__init__.py
unweb.iptc.egg-info/PKG-INFO
unweb.iptc.egg-info/SOURCES.txt
unweb.iptc.egg-info/dependency_links.txt
unweb.iptc.egg-info/entry_points.txt
unweb.iptc.egg-info/namespace_packages.txt
unweb.iptc.egg-info/not-zip-safe
unweb.iptc.egg-info/paster_plugins.txt
unweb.iptc.egg-info/requires.txt
unweb.iptc.egg-info/top_level.txt
unweb/iptc/__init__.py
unweb/iptc/browser.txt
unweb/iptc/configure.zcml
unweb/iptc/sample.jpg
unweb/iptc/subscribers.py
unweb/iptc/testing.py
unweb/iptc/tests.py