Metadata-Version: 1.1
Name: unweb.iptc
Version: 0.4
Summary: IPTC metadata extraction and storage for images in Plone
Home-page: http://pypi.python.org/pypi/unweb.iptc/
Author: Dimitris Moraitis
Author-email: dimo@unweb.me
License: GPL
Keywords: image photo metadata IPTC keywords plone zope
Platform: UNKNOWN
Classifier: Framework :: Plone
Classifier: Programming Language :: Python
Classifier: Topic :: Multimedia :: Graphics
